dj_haystack_url.py
dj_haystack_url-0.2.0.dist-info/DESCRIPTION.rst
dj_haystack_url-0.2.0.dist-info/METADATA
dj_haystack_url-0.2.0.dist-info/metadata.json
dj_haystack_url-0.2.0.dist-info/RECORD
dj_haystack_url-0.2.0.dist-info/top_level.txt
dj_haystack_url-0.2.0.dist-info/WHEEL
