Metadata-Version: 2.0
Name: dj-haystack-url
Version: 0.2.0
Summary: Haystack configuration from environment variable
Home-page: https://github.com/simpleenergy/dj-haystack-url
Author: Piper Merriam
Author-email: piper@simpleenergy.com
License: MIT
Keywords: dj-haystack-url
Platform: UNKNOWN
Classifier: Development Status :: 2 - Pre-Alpha
Classifier: Intended Audience :: Developers
Classifier: License :: OSI Approved :: BSD License
Classifier: Natural Language :: English
Classifier: Programming Language :: Python :: 2
Classifier: Programming Language :: Python :: 2.6
Classifier: Programming Language :: Python :: 2.7
Classifier: Programming Language :: Python :: 3
Classifier: Programming Language :: Python :: 3.3
Classifier: Programming Language :: Python :: 3.4
